macro_gridder/__init__.py
macro_gridder/core.py
macro_gridder/realtime.py
macro_gridder/utils.py
macro_gridder/visualization.py
macro_gridder-0.1.4.dist-info/LICENSE
macro_gridder-0.1.4.dist-info/METADATA
macro_gridder-0.1.4.dist-info/WHEEL
macro_gridder-0.1.4.dist-info/top_level.txt
macro_gridder-0.1.4.dist-info/RECORD
