Metadata-Version: 2.2
Name: macro_gridder
Version: 0.1.4
Summary: A library for real-time macro grid calculation for stock daily and tick-level data
Author-email: JasonJiang0303 <chinese88+0303@2925.com>
License: MIT
Project-URL: Homepage, https://github.com/JasonJiang0303/macro-gridder
Project-URL: Bug Tracker, https://github.com/JasonJiang0303/macro-gridder/issues
Classifier: Programming Language :: Python :: 3
Classifier: License :: OSI Approved :: MIT License
Classifier: Operating System :: OS Independent
Requires-Python: >=3.7
License-File: LICENSE
Requires-Dist: protobuf>=3.12.0
